ackl/__init__.py
ackl/kernels.py
ackl/metrics.py
ackl/gui/__init__.py
ackl/gui/run.py
ackl/gui/static/bootstrap.css
ackl/gui/static/bootstrap.js
ackl/gui/static/jquery-3.3.1.min.js
ackl/gui/static/jquery.blockUI.js
ackl/gui/static/jquery.form.min.js
ackl/gui/static/sample.csv
ackl/gui/templates/home.html
ackl-2.2.0.dist-info/LICENSE
ackl-2.2.0.dist-info/METADATA
ackl-2.2.0.dist-info/WHEEL
ackl-2.2.0.dist-info/top_level.txt
ackl-2.2.0.dist-info/RECORD
