Metadata-Version: 2.1
Name: ackl
Version: 2.2.0
Summary: A Python library for kernels used in analytical chemistry
Home-page: https://github.com/zhangys11/ack
Author: Yinsheng Zhang (Ph.D.)
Author-email: oo@zju.edu.cn
Project-URL: Bug Tracker, https://github.com/zhangys11/ack/issues
Classifier: Programming Language :: Python :: 3
Classifier: License :: OSI Approved :: MIT License
Classifier: Operating System :: OS Independent
Classifier: Topic :: Scientific/Engineering :: Mathematics
Requires-Python: >=3.6
License-File: LICENSE
Requires-Dist: scikit-learn
Requires-Dist: scipy
Requires-Dist: matplotlib
Requires-Dist: numpy
Requires-Dist: cla
Requires-Dist: opencv-python
Requires-Dist: flaskwebgui
